prefect/.prefectignore
prefect/__init__.py
prefect/_version.py
prefect/agent.py
prefect/context.py
prefect/engine.py
prefect/exceptions.py
prefect/filesystems.py
prefect/flows.py
prefect/futures.py
prefect/manifests.py
prefect/plugins.py
prefect/profiles.toml
prefect/py.typed
prefect/results.py
prefect/serializers.py
prefect/settings.py
prefect/states.py
prefect/task_runners.py
prefect/tasks.py
prefect/variables.py
prefect/_internal/__init__.py
prefect/_internal/_logging.py
prefect/_internal/pytz.py
prefect/_internal/compatibility/__init__.py
prefect/_internal/compatibility/deprecated.py
prefect/_internal/compatibility/experimental.py
prefect/_internal/concurrency/__init__.py
prefect/_internal/concurrency/api.py
prefect/_internal/concurrency/calls.py
prefect/_internal/concurrency/cancellation.py
prefect/_internal/concurrency/event_loop.py
prefect/_internal/concurrency/inspection.py
prefect/_internal/concurrency/primitives.py
prefect/_internal/concurrency/services.py
prefect/_internal/concurrency/threads.py
prefect/_internal/concurrency/waiters.py
prefect/_internal/pydantic/__init__.py
prefect/_internal/pydantic/v2_validated_func.py
prefect/_internal/schemas/__init__.py
prefect/_internal/schemas/bases.py
prefect/_internal/schemas/fields.py
prefect/_internal/schemas/serializers.py
prefect/_internal/schemas/transformations.py
prefect/_internal/schemas/validators.py
prefect/_vendor/__init__.py
prefect/_vendor/fastapi/__init__.py
prefect/_vendor/fastapi/applications.py
prefect/_vendor/fastapi/background.py
prefect/_vendor/fastapi/concurrency.py
prefect/_vendor/fastapi/datastructures.py
prefect/_vendor/fastapi/encoders.py
prefect/_vendor/fastapi/exception_handlers.py
prefect/_vendor/fastapi/exceptions.py
prefect/_vendor/fastapi/logger.py
prefect/_vendor/fastapi/param_functions.py
prefect/_vendor/fastapi/params.py
prefect/_vendor/fastapi/requests.py
prefect/_vendor/fastapi/responses.py
prefect/_vendor/fastapi/routing.py
prefect/_vendor/fastapi/staticfiles.py
uriel_pc_tests-1.0.1.dist-info/LICENSE
uriel_pc_tests-1.0.1.dist-info/METADATA
uriel_pc_tests-1.0.1.dist-info/WHEEL
uriel_pc_tests-1.0.1.dist-info/top_level.txt
uriel_pc_tests-1.0.1.dist-info/RECORD
