Metadata-Version: 2.1
Name: uriel-pc-tests
Version: 1.0.1
Summary: Workflow orchestration and management.
Home-page: https://www.prefect.io
Author: Prefect Technologies, Inc.
Author-email: help@prefect.io
License: UNKNOWN
Project-URL: Changelog, https://github.com/PrefectHQ/prefect/blob/main/RELEASE-NOTES.md
Project-URL: Documentation, https://docs.prefect.io
Project-URL: Source, https://github.com/PrefectHQ/prefect
Project-URL: Tracker, https://github.com/PrefectHQ/prefect/issues
Platform: UNKNOWN
Classifier: Natural Language :: English
Classifier: Intended Audience :: Developers
Classifier: Intended Audience :: System Administrators
Classifier: License :: OSI Approved :: Apache Software License
Classifier: Programming Language :: Python :: 3 :: Only
Classifier: Programming Language :: Python :: 3.8
Classifier: Programming Language :: Python :: 3.9
Classifier: Programming Language :: Python :: 3.10
Classifier: Programming Language :: Python :: 3.11
Classifier: Topic :: Software Development :: Libraries
Requires-Python: >=3.8
Requires-Dist: anyio <4.0.0,>=3.7.1
Requires-Dist: asgi-lifespan <3.0,>=1.0
Requires-Dist: cloudpickle <3.0,>=2.0
Requires-Dist: coolname <3.0.0,>=1.0.4
Requires-Dist: croniter <2.0.0,>=1.0.12
Requires-Dist: fsspec >=2022.5.0
Requires-Dist: graphviz >=0.20.1
Requires-Dist: griffe >=0.20.0
Requires-Dist: httpcore <2.0.0,>=0.15.0
Requires-Dist: httpx[http2] !=0.23.2,>=0.23
Requires-Dist: jsonpatch <2.0,>=1.32
Requires-Dist: jsonschema <5.0.0,>=3.2.0
Requires-Dist: orjson <4.0,>=3.7
Requires-Dist: packaging <24.3,>=21.3
Requires-Dist: pathspec >=0.8.0
Requires-Dist: pendulum <3.0.0,>=2.1.2
Requires-Dist: pydantic[email] !=2.0.0,!=2.0.1,!=2.1.0,<3.0.0,>=1.10.0
Requires-Dist: python-dateutil <3.0.0,>=2.8.2
Requires-Dist: python-slugify <9.0,>=5.0
Requires-Dist: pyyaml <7.0.0,>=5.4.1
Requires-Dist: rich <14.0,>=11.0
Requires-Dist: ruamel.yaml >=0.17.0
Requires-Dist: sniffio <2.0.0,>=1.3.0
Requires-Dist: starlette <0.28.0,>=0.27.0
Requires-Dist: toml >=0.10.0
Requires-Dist: typing-extensions <5.0.0,>=4.5.0
Requires-Dist: ujson <6.0.0,>=5.8.0
Requires-Dist: uvicorn >=0.14.0
Requires-Dist: websockets <12.0,>=10.4
Requires-Dist: importlib-metadata >=4.4 ; python_version < "3.10"
Provides-Extra: notifications
Requires-Dist: apprise <2.0.0,>=1.1.0 ; extra == 'notifications'
